pyfds/__init__.py
pyfds/acoustic_flow.py
pyfds/acoustics.py
pyfds/coupled_fields.py
pyfds/coupling.py
pyfds/electrostatics.py
pyfds/fields.py
pyfds/gfx.py
pyfds/nonlinear_acoustics.py
pyfds/regions.py
pyfds/thermal.py
pyfds-0.3.1.dist-info/AUTHORS.rst
pyfds-0.3.1.dist-info/LICENSE
pyfds-0.3.1.dist-info/METADATA
pyfds-0.3.1.dist-info/WHEEL
pyfds-0.3.1.dist-info/top_level.txt
pyfds-0.3.1.dist-info/RECORD
