Metadata-Version: 2.1
Name: pyfds
Version: 0.3.1
Summary: Modular field simulation tool using finite differences.
Home-page: https://emt.uni-paderborn.de
Author: Leander Claes
Author-email: Leander Claes <claes@emt.uni-paderborn.de>
License: Copyright (c) 2017 Leander Claes
Project-URL: homepage, https://emt.uni-paderborn.de
Project-URL: source, https://github.com/emtpb/pyfds
Project-URL: tracker, https://github.com/emtpb/pyfds/issues
Classifier: Development Status :: 2 - Pre-Alpha
Classifier: Intended Audience :: Science/Research
Classifier: License :: OSI Approved :: BSD License
Classifier: Programming Language :: Python :: 3
Classifier: Topic :: Scientific/Engineering
Requires-Python: >=3.7
License-File: LICENSE
License-File: AUTHORS.rst
Requires-Dist: matplotlib
Requires-Dist: numpy
Requires-Dist: scipy
Provides-Extra: doc
Requires-Dist: setuptools-scm ; extra == 'doc'
Requires-Dist: sphinx ; extra == 'doc'
Requires-Dist: sphinx-rtd-theme ; extra == 'doc'
Provides-Extra: test
Requires-Dist: pytest ; extra == 'test'
